{
  "title": "Tondela-Benfica: 5 Secrets They DON'T Want You To Know!",
  "date": "2026-02-01",
  "word_count": 2346,
  "images": [
    "https://images.pexels.com/photos/27521406/pexels-photo-27521406.jpeg?auto=compress&cs=tinysrgb&h=650&w=940",
    "https://images.pexels.com/photos/28297583/pexels-photo-28297583.jpeg?auto=compress&cs=tinysrgb&h=650&w=940",
    "https://images.pexels.com/photos/27825960/pexels-photo-27825960.jpeg?auto=compress&cs=tinysrgb&h=650&w=940",
    "https://images.pexels.com/photos/26868175/pexels-photo-26868175.jpeg?auto=compress&cs=tinysrgb&h=650&w=940",
    "https://images.pexels.com/photos/19384227/pexels-photo-19384227.jpeg?auto=compress&cs=tinysrgb&h=650&w=940"
  ],
  "videos": [],
  "frontmatter": {
    "title": "Tondela-Benfica: 5 Secrets They DON'T Want You To Know!",
    "description": "Breaking: Tondela-Benfica news you can't miss! Get exclusive insights, match results & future predictions NOW before it's too late! #TondelaBenfica",
    "slug": "tondela-benfica-secrets",
    "date": "2026-02-01",
    "author": "Sarah Mitchell",
    "tags": [
      "Tondela-Benfica",
      "Tondela",
      "Benfica",
      "Trending",
      "Viral"
    ],
    "keywords": [
      "tondela - benfica",
      "tondela benfica ii",
      "tondela benfica b",
      "tondela benfica bilhetes",
      "tondela benfica 2026",
      "tondela benfica resultado",
      "tondela benfica ma\u00e7 kadrosu",
      "tondela benfica b hoje",
      "tondela benfica u19",
      "tondela benfica sub 15"
    ],
    "category": "trending",
    "featured": true,
    "draft": false,
    "image": "https://images.pexels.com/photos/27521406/pexels-photo-27521406.jpeg?auto=compress&cs=tinysrgb&h=650&w=940"
  },
  "keywords": {
    "topic": "tondela - benfica",
    "title": "Tondela-Benfica: 5 Secrets They DON'T Want You To Know!",
    "primary_keyword": "tondela - benfica",
    "secondary_keywords": [
      "tondela - benfica",
      "tondela benfica ii",
      "tondela benfica b",
      "tondela benfica bilhetes",
      "tondela benfica 2026",
      "tondela benfica resultado",
      "tondela benfica ma\u00e7 kadrosu",
      "tondela benfica b hoje",
      "tondela benfica u19",
      "tondela benfica sub 15"
    ],
    "long_tail_keywords": [
      "what is tondela - benfica game",
      "how to watch tondela - benfica",
      "why is tondela - benfica trending",
      "when is tondela - benfica match",
      "where is tondela - benfica played",
      "latest tondela - benfica news",
      "best tondela - benfica highlights",
      "top tondela - benfica players"
    ],
    "suggested_headings": [
      "What is the Buzz Around Tondela - Benfica?",
      "Tondela Benfica II & B Teams: What's the Difference?",
      "Where to Find Tondela Benfica Bilhetes (Tickets)?",
      "Tondela Benfica 2026: Early Predictions & Analysis",
      "Tondela Benfica Resultado: Latest Match Results Revealed",
      "Tondela Benfica Ma\u00e7 Kadrosu: Who's Playing?",
      "Tondela Benfica B Hoje: Today's Game Details",
      "Tondela Benfica U19 & Sub 15: Future Stars to Watch",
      "CD Tondela vs. SL Benfica: Head-to-Head Analysis",
      "Why Tondela vs Benfica is a Must-Watch Game"
    ],
    "hashtags": [
      "#Tondela-Benfica",
      "#Tondela",
      "#Benfica",
      "#Trending",
      "#Viral",
      "#News",
      "#Breaking",
      "#MustRead",
      "#TondelaBenfica",
      "#Football",
      "#Soccer"
    ],
    "meta_description": "Breaking: Tondela-Benfica news you can't miss! Get exclusive insights, match results & future predictions NOW before it's too late! #TondelaBenfica",
    "slug": "tondela-benfica-secrets",
    "schema_type": "NewsArticle",
    "viral_hooks": [
      "The internet is exploding over Tondela-Benfica, and here's why...",
      "Forget everything you thought you knew about Tondela-Benfica...",
      "Tondela-Benfica is more than just a game; it's a phenomenon..."
    ],
    "click_triggers": [
      "exclusive",
      "breaking",
      "finally",
      "revealed",
      "shocking",
      "unbelievable",
      "must-see",
      "secret"
    ],
    "google_suggestions": [
      "tondela - benfica",
      "tondela benfica ii",
      "tondela benfica b",
      "tondela benfica bilhetes",
      "tondela benfica 2026",
      "tondela benfica resultado",
      "tondela benfica ma\u00e7 kadrosu",
      "tondela benfica b hoje",
      "tondela benfica u19",
      "tondela benfica sub 15"
    ],
    "keyword_patterns": [
      "what is tondela - benfica",
      "how to tondela - benfica",
      "why is tondela - benfica",
      "when is tondela - benfica",
      "where is tondela - benfica",
      "who is tondela - benfica",
      "best tondela - benfica",
      "top tondela - benfica",
      "latest tondela - benfica",
      "tondela - benfica news",
      "tondela - benfica update",
      "tondela - benfica today",
      "tondela - benfica 2026",
      "tondela - benfica live",
      "tondela - benfica highlights",
      "tondela - benfica results",
      "tondela - benfica latest news",
      "tondela - benfica breaking",
      "tondela - benfica explained",
      "tondela - benfica guide"
    ]
  }
}