{
  "title": "CBS EXPOSED: 7 Shocking Facts You NEED to Know!",
  "date": "2026-02-02",
  "word_count": 1784,
  "images": [
    "https://images.pexels.com/photos/18646440/pexels-photo-18646440.jpeg?auto=compress&cs=tinysrgb&h=650&w=940",
    "https://images.pexels.com/photos/19251599/pexels-photo-19251599.jpeg?auto=compress&cs=tinysrgb&h=650&w=940",
    "https://images.pexels.com/photos/16118554/pexels-photo-16118554.jpeg?auto=compress&cs=tinysrgb&h=650&w=940",
    "https://images.pexels.com/photos/19001991/pexels-photo-19001991.jpeg?auto=compress&cs=tinysrgb&h=650&w=940",
    "https://images.pexels.com/photos/18609900/pexels-photo-18609900.jpeg?auto=compress&cs=tinysrgb&h=650&w=940"
  ],
  "videos": [],
  "frontmatter": {
    "title": "CBS EXPOSED: 7 Shocking Facts You NEED to Know!",
    "description": "CBS News is blowing up! Don't miss the latest updates, scandals & schedule changes. Get the inside scoop before it's too late! #CBS #News",
    "slug": "cbs-exposed-news-schedule",
    "date": "2026-02-02",
    "author": "Robert Taylor",
    "tags": [
      "Cbs",
      "Trending",
      "Viral",
      "News",
      "Breaking"
    ],
    "keywords": [
      "cbs",
      "cbs news",
      "cbs sports",
      "cbs sunday morning",
      "cbs schedule tonight",
      "cbs sports network",
      "cbs cheyenne",
      "cbs schedule",
      "cbs grammys",
      "cbs evening news"
    ],
    "category": "trending",
    "featured": true,
    "draft": false,
    "image": "https://images.pexels.com/photos/18646440/pexels-photo-18646440.jpeg?auto=compress&cs=tinysrgb&h=650&w=940"
  },
  "keywords": {
    "topic": "cbs",
    "title": "CBS EXPOSED: 7 Shocking Facts You NEED to Know!",
    "primary_keyword": "cbs",
    "secondary_keywords": [
      "cbs",
      "cbs news",
      "cbs sports",
      "cbs sunday morning",
      "cbs schedule tonight",
      "cbs sports network",
      "cbs cheyenne",
      "cbs schedule",
      "cbs grammys",
      "cbs evening news"
    ],
    "long_tail_keywords": [
      "what is cbs and why",
      "how to watch cbs live",
      "why is cbs trending now",
      "when is cbs schedule update",
      "where to watch cbs sports"
    ],
    "suggested_headings": [
      "What is CBS and Why Is It Trending?",
      "Breaking News: CBS's Latest Headlines",
      "CBS Schedule Tonight: Don't Miss These Shows!",
      "CBS Sports Network: Live Games and Highlights",
      "How to Watch CBS Online: Streaming Options",
      "CBS Evening News: Stay Informed With Top Stories",
      "The Future of CBS: What's Next for the Network?"
    ],
    "hashtags": [
      "#Cbs",
      "#Trending",
      "#Viral",
      "#News",
      "#Breaking",
      "#MustRead"
    ],
    "meta_description": "CBS News is blowing up! Don't miss the latest updates, scandals & schedule changes. Get the inside scoop before it's too late! #CBS #News",
    "slug": "cbs-exposed-news-schedule",
    "schema_type": "NewsArticle",
    "viral_hooks": [
      "Is CBS about to change forever? The answer will shock you.",
      "The truth about CBS that they don't want you to know...",
      "CBS is under fire and here's why everyone is talking about it."
    ],
    "click_triggers": [
      "breaking",
      "revealed",
      "exclusive",
      "finally",
      "shocking",
      "must-see"
    ],
    "google_suggestions": [
      "cbs",
      "cbs news",
      "cbs sports",
      "cbs sunday morning",
      "cbs schedule tonight",
      "cbs sports network",
      "cbs cheyenne",
      "cbs schedule",
      "cbs grammys",
      "cbs evening news"
    ],
    "keyword_patterns": [
      "what is cbs",
      "how to cbs",
      "why is cbs",
      "when is cbs",
      "where is cbs",
      "who is cbs",
      "best cbs",
      "top cbs",
      "latest cbs",
      "cbs news",
      "cbs update",
      "cbs today",
      "cbs 2026",
      "cbs live",
      "cbs highlights",
      "cbs results",
      "cbs latest news",
      "cbs breaking",
      "cbs explained",
      "cbs guide"
    ]
  }
}